edc_action_item/__init__.py
edc_action_item/_version.py
edc_action_item/action.py
edc_action_item/action_item_notification.py
edc_action_item/action_with_notification.py
edc_action_item/admin_site.py
edc_action_item/apps.py
edc_action_item/auth_objects.py
edc_action_item/auths.py
edc_action_item/choices.py
edc_action_item/constants.py
edc_action_item/create_action_item.py
edc_action_item/create_or_update_action_type.py
edc_action_item/data_fixers.py
edc_action_item/decorators.py
edc_action_item/delete_action_item.py
edc_action_item/exceptions.py
edc_action_item/fieldsets.py
edc_action_item/get_action_type.py
edc_action_item/identifiers.py
edc_action_item/managers.py
edc_action_item/modeladmin_mixins.py
edc_action_item/offline_models.py
edc_action_item/post_migrate_signals.py
edc_action_item/send_email.py
edc_action_item/site_action_items.py
edc_action_item/stubs.py
edc_action_item/system_checks.py
edc_action_item/urls.py
edc_action_item/utils.py
edc_action_item/visit_schedule_mixin.py
edc_action_item/admin/__init__.py
edc_action_item/admin/action_item_admin.py
edc_action_item/admin/action_type_admin.py
edc_action_item/forms/__init__.py
edc_action_item/forms/action_item_crf_form_mixin.py
edc_action_item/forms/action_item_form.py
edc_action_item/forms/action_item_form_mixin.py
edc_action_item/forms/action_type_form.py
edc_action_item/management/commands/inspect_action_items.py
edc_action_item/migrations/0001_initial.py
edc_action_item/migrations/0002_auto_20180109_1117.py
edc_action_item/migrations/0003_auto_20180116_1528.py
edc_action_item/migrations/0004_auto_20180319_2128.py
edc_action_item/migrations/0005_auto_20180409_1005.py
edc_action_item/migrations/0006_auto_20180707_1659.py
edc_action_item/migrations/0007_auto_20180707_1715.py
edc_action_item/migrations/0008_auto_20180809_0303.py
edc_action_item/migrations/0009_auto_20180927_0306.py
edc_action_item/migrations/0010_auto_20181009_0445.py
edc_action_item/migrations/0011_auto_20181009_2236.py
edc_action_item-1.0.3.dist-info/licenses/AUTHORS
edc_action_item-1.0.3.dist-info/licenses/LICENSE
edc_action_item-1.0.3.dist-info/METADATA
edc_action_item-1.0.3.dist-info/WHEEL
edc_action_item-1.0.3.dist-info/top_level.txt
edc_action_item-1.0.3.dist-info/RECORD
